{"id": 0, "utter": "blue", "env": [{"shape": "triangle", "color": "blue"}, {"shape": "square", "color": "blue"}, {"shape": "circle", "color": "blue"}], "target": [0.3333333333333333, 0.3333333333333333, 0.3333333333333333]}{"id": 0, "utter": "circle", "env": [{"shape": "triangle", "color": "blue"}, {"shape": "square", "color": "blue"}, {"shape": "circle", "color": "blue"}], "target": [0, 0, 1]}{"id": 0, "utter": "square", "env": [{"shape": "triangle", "color": "blue"}, {"shape": "square", "color": "blue"}, {"shape": "circle", "color": "blue"}], "target": [0, 1, 0]}{"id": 0, "utter": "triangle", "env": [{"shape": "triangle", "color": "blue"}, {"shape": "square", "color": "blue"}, {"shape": "circle", "color": "blue"}], "target": [1, 0, 0]}{"id": 1, "utter": "blue", "env": [{"shape": "square", "color": "blue"}, {"shape": "circle", "color": "blue"}, {"shape": "circle", "color": "green"}], "target": [0.4000000000000001, 0.6, 0]}{"id": 1, "utter": "green", "env": [{"shape": "square", "color": "blue"}, {"shape": "circle", "color": "blue"}, {"shape": "circle", "color": "green"}], "target": [0, 0, 1]}{"id": 1, "utter": "circle", "env": [{"shape": "square", "color": "blue"}, {"shape": "circle", "color": "blue"}, {"shape": "circle", "color": "green"}], "target": [0, 0.6, 0.4000000000000001]}{"id": 1, "utter": "square", "env": [{"shape": "square", "color": "blue"}, {"shape": "circle", "color": "blue"}, {"shape": "circle", "color": "green"}], "target": [1, 0, 0]}{"id": 2, "utter": "blue", "env": [{"shape": "square", "color": "blue"}, {"shape": "circle", "color": "blue"}, {"shape": "square", "color": "green"}], "target": [0.6, 0.4000000000000001, 0]}{"id": 2, "utter": "green", "env": [{"shape": "square", "color": "blue"}, {"shape": "circle", "color": "blue"}, {"shape": "square", "color": "green"}], "target": [0, 0, 1]}{"id": 2, "utter": "circle", "env": [{"shape": "square", "color": "blue"}, {"shape": "circle", "color": "blue"}, {"shape": "square", "color": "green"}], "target": [0, 1, 0]}{"id": 2, "utter": "square", "env": [{"shape": "square", "color": "blue"}, {"shape": "circle", "color": "blue"}, {"shape": "square", "color": "green"}], "target": [0.6, 0, 0.4000000000000001]}{"id": 3, "utter": "blue", "env": [{"shape": "square", "color": "blue"}, {"shape": "circle", "color": "blue"}, {"shape": "triangle", "color": "green"}], "target": [0.49999999999999994, 0.49999999999999994, 0]}{"id": 3, "utter": "green", "env": [{"shape": "square", "color": "blue"}, {"shape": "circle", "color": "blue"}, {"shape": "triangle", "color": "green"}], "target": [0, 0, 1]}{"id": 3, "utter": "circle", "env": [{"shape": "square", "color": "blue"}, {"shape": "circle", "color": "blue"}, {"shape": "triangle", "color": "green"}], "target": [0, 1, 0]}{"id": 3, "utter": "square", "env": [{"shape": "square", "color": "blue"}, {"shape": "circle", "color": "blue"}, {"shape": "triangle", "color": "green"}], "target": [1, 0, 0]}{"id": 3, "utter": "triangle", "env": [{"shape": "square", "color": "blue"}, {"shape": "circle", "color": "blue"}, {"shape": "triangle", "color": "green"}], "target": [0, 0, 1]}{"id": 4, "utter": "blue", "env": [{"shape": "square", "color": "blue"}, {"shape": "circle", "color": "blue"}, {"shape": "circle", "color": "pink"}], "target": [0.4000000000000001, 0.6, 0]}{"id": 4, "utter": "pink", "env": [{"shape": "square", "color": "blue"}, {"shape": "circle", "color": "blue"}, {"shape": "circle", "color": "pink"}], "target": [0, 0, 1]}{"id": 4, "utter": "circle", "env": [{"shape": "square", "color": "blue"}, {"shape": "circle", "color": "blue"}, {"shape": "circle", "color": "pink"}], "target": [0, 0.6, 0.4000000000000001]}{"id": 4, "utter": "square", "env": [{"shape": "square", "color": "blue"}, {"shape": "circle", "color": "blue"}, {"shape": "circle", "color": "pink"}], "target": [1, 0, 0]}